{
  "name": "Maria Neal",
  "age": 39,
  "address": {
    "street": "Jofim Ridge",
    "city": "Hijihfo",
    "state": "AK",
    "zip": "84728"
  },
  "contact": {
    "phone": "(786) 651-4547",
    "servicePhone": "800442834"
  },
  "birthday": "2004-03-11T00:41:52.973Z",
  "ip": "230.122.223.228",
  "foo": "bar",
  "profile": {
    "about": "Tewtit pi maz limizizi zene agokem lonjojoc dejbagele rociole zusrebet vi miwel cebe acapa vajjes zabuvuc ipo gefbe. Piokopa li tetaded ajeolko kuvi su fag toov pejum ojifolip puwibko bavavzag. Jev bugov rib pa kughita ritoz wa gozsuh wugukov ervontof fanfinweb macut rap mi.",
    "bio": "Ker riefo reukegog darebmo dar kub mesga ki al begico iwisoh ho fo ceckimzo du mivsena. Wamgeh gokec pi odosiwol idevuwje por dacu cah tolradmo zefelefef owcos esulagu ruwe nizujfa. Hestef lafworjof ja ofi timsim jozic hu tofapihek ti avibi ki ozi waknac uni celohop. Zevnun tovejjah pujitlin saj fe bif vu ebhunru bum cu amulez tilo lew sitja zuahu duj lihaule. Pappesta madile kij vihec nukna ep tibad cewepofe lilipu jas og buppob lutono. Geihiwun za ule be osefov og leiba onuhuw wali wavmi oweejoomi bo puah iheecva."
  },
  "apiKey": "d8405cacd5b0f7a81bf70d61e8be3710b77cf42c0744032e55b80125b6646519",
  "currency": {
    "code": "HUF",
    "name": "Hungary Forint"
  }
}