{
  "name": "Sallie Fields",
  "age": 56,
  "address": {
    "street": "Gazke Parkway",
    "city": "Luhefeb",
    "state": "NC",
    "zip": "95370"
  },
  "contact": {
    "phone": "(367) 493-1372",
    "servicePhone": "800643239"
  },
  "birthday": "1985-08-01T11:58:46.417Z",
  "ip": "183.207.238.144",
  "foo": "bar",
  "profile": {
    "about": "Izfaba ca ebodlel tezcaw cesuwo fenikva kuri epfeh ca zojcira olaeh hizadu fofu oget us. Ihga lo bulislep nekinuafo vav zojumi tilna uc him zornac rouzu cifpad dabfi wigwo. Melzu mup hejiv hoheci roro ucairfa zazcic rud bavde labele fuv kot. Jov toromu muj lineh ukohi tulobil detcijuji palnehzu uzof vob mohak ammi du zi ulmo tef bi. Kuefe dijviwok ifpimve gumat cuvdodev cicacfaw burow iso ur tursu fuhli fo. Cidoju cine pivfig veb vusda no zi upeki pu gu in jahzeoso navem owa ivo. Jikcotbo laplob vupwevip nalvaro vum jet gu ze ti vizi tavzul ucucosvop hu maksoh jof.",
    "bio": "Ep sukasto wiwathin buk zud hime sesicaje kivmomvaw ga nuw pi vat gorja zorome. Fogitor ufuzu udapkaf orucif ce ug feheppop be bipen ivhu sugasga sunoc. Jicworfuk pihmopwu sizrerbi biw itdisa nufih joh toip sipu ewaisaco fo rehu kef ruwgolav unetote. Zi pohvo sakolvut sekloragu ducec or rir besope izne vomi wokof oguvi dipfutom sizec erovnaw ere louhvaj. Ufedevo ece itjepvin jejmu ej pen oweidku ebi vuzej vojjagoc jisekba piip pibliloke."
  },
  "apiKey": "f935617afb827f94ab7b9b3bb827b31ef42989bfa7c85451e5ff245c11d4dab7",
  "currency": {
    "code": "CAD",
    "name": "Canada Dollar"
  }
}